4chan-0.0.4.dist-info/DESCRIPTION.rst
4chan-0.0.4.dist-info/METADATA
4chan-0.0.4.dist-info/RECORD
4chan-0.0.4.dist-info/WHEEL
4chan-0.0.4.dist-info/entry_points.txt
4chan-0.0.4.dist-info/metadata.json
4chan-0.0.4.dist-info/top_level.txt
chan/__init__.py
chan/__main__.py
chan/chan.py
