Metadata-Version: 2.0
Name: 4chan
Version: 0.0.4
Summary: A python script that downloads all images from a 4chan thread.
Home-page: https://github.com/AnthonyBloomer/chan
Author: Anthony Bloomer
Author-email: ant0@protonmail.ch
License: UNKNOWN
Platform: UNKNOWN
Classifier: Intended Audience :: Developers
Classifier: License :: OSI Approved :: MIT License
Classifier: Topic :: Software Development :: Libraries
Classifier: Programming Language :: Python :: 2.7
